paik2json/__init__.py
paik2json/line.py
paik2json/line_manager.py
paik2json/parser.py
paik2json-0.2.1.dist-info/LICENSE
paik2json-0.2.1.dist-info/METADATA
paik2json-0.2.1.dist-info/WHEEL
paik2json-0.2.1.dist-info/top_level.txt
paik2json-0.2.1.dist-info/RECORD
