Metadata-Version: 2.1
Name: paik2json
Version: 0.2.1
Summary: convert paik to json
Home-page: https://github.com/paikwiki/paik2json
Author: paikwiki
Author-email: paikwiki@gmail.com
License-File: LICENSE
